life_in_tkk/__init__.py
life_in_tkk/tkkcourse.py
life_in_tkk/tkkhtml.py
life_in_tkk/tkktime.py
life_in_tkk/tkktools.py
life_in_tkk-0.0.2.2.dist-info/LICENSE
life_in_tkk-0.0.2.2.dist-info/METADATA
life_in_tkk-0.0.2.2.dist-info/WHEEL
life_in_tkk-0.0.2.2.dist-info/top_level.txt
life_in_tkk-0.0.2.2.dist-info/RECORD
