Metadata-Version: 2.1
Name: life-in-tkk
Version: 0.0.2.2
Summary: A library to help tkk(xujc)'s student feel relax on their daliy campus life
Home-page: https://github.com/Mirasire/Life-In-Tkk
Author: mirasire
Author-email: mes2dasuan@outlook.com
License: MIT License
Platform: UNKNOWN
Classifier: Development Status :: 3 - Alpha
Classifier: Intended Audience :: Developers
Classifier: Programming Language :: Python :: 3
Classifier: Programming Language :: Python :: 3.5
Classifier: Programming Language :: Python :: 3.6
Classifier: Programming Language :: Python :: 3.7
Classifier: Programming Language :: Python :: 3.8
Classifier: Topic :: Utilities
Classifier: License :: OSI Approved :: MIT License
Requires-Dist: Pillow (>=8.0.1)
Requires-Dist: selenium (>=3.141.0)
Requires-Dist: requests (>=2.22.0)
Requires-Dist: beautifulsoup4 (>=4.8.2)
Requires-Dist: pytesseract (>=0.3.6)
Requires-Dist: tesseract (>=0.1.3)
Requires-Dist: numpy (>=1.17.4)
